odoo/addons/sale_order_line_multi_warehouse_widget/README.rst
odoo/addons/sale_order_line_multi_warehouse_widget/__init__.py
odoo/addons/sale_order_line_multi_warehouse_widget/__manifest__.py
odoo/addons/sale_order_line_multi_warehouse_widget/models/__init__.py
odoo/addons/sale_order_line_multi_warehouse_widget/models/sale_order_line.py
odoo/addons/sale_order_line_multi_warehouse_widget/readme/CONTRIBUTORS.md
odoo/addons/sale_order_line_multi_warehouse_widget/readme/DESCRIPTION.md
odoo/addons/sale_order_line_multi_warehouse_widget/readme/USAGE.md
odoo/addons/sale_order_line_multi_warehouse_widget/static/description/icon.png
odoo/addons/sale_order_line_multi_warehouse_widget/static/description/index.html
odoo/addons/sale_order_line_multi_warehouse_widget/static/src/widgets/qty_at_date_by_warehouse_widget.esm.js
odoo/addons/sale_order_line_multi_warehouse_widget/static/src/widgets/qty_at_date_by_warehouse_widget.xml
odoo/addons/sale_order_line_multi_warehouse_widget/tests/__init__.py
odoo/addons/sale_order_line_multi_warehouse_widget/tests/test_so_line_multiwarehouse_widget.py
odoo/addons/sale_order_line_multi_warehouse_widget/views/sale_order_views.xml
odoo_addon_sale_order_line_multi_warehouse_widget-16.0.1.0.0.1.dist-info/METADATA
odoo_addon_sale_order_line_multi_warehouse_widget-16.0.1.0.0.1.dist-info/WHEEL
odoo_addon_sale_order_line_multi_warehouse_widget-16.0.1.0.0.1.dist-info/top_level.txt
odoo_addon_sale_order_line_multi_warehouse_widget-16.0.1.0.0.1.dist-info/RECORD
